{
    "landing": {
        "common": {
            "SUBMIT": "Оставить заявку",
            "CLOSE": "Закрыть",
            "NEXT": "Далее"
        },
        "header": {
            "productName": "Помогатель"
        },
        "main": {
            "TITLE": "Кадровое агентство",
            "TITLE_BADGE": "Помогатель.ру",
            "DESCRIPTION": "14 лет мы помогаем в поиске<br> домашнего персонала"
        },
        "main_info": {
            "DESCRIPTION": "Цена за наши услуги - <span class='main-info__accent'>фиксированная.</span> Зависит от ваших потребностей, а не от зарплаты вашего будущего работника, как в других агентствах"
        },
        "tariffs": {
            "TITLE": "Тарифы",
            "tariff_list": {
                "standart": {
                    "TITLE": "Стандарт",
                    "DESCRIPTION": "Для эффективного поиска",
                    "OPTION_1": "Подберём до 6 подходящих анкет работников",
                    "OPTION_2": "Предложим 3 лучших кандидата на выбор",
                    "PRICE": "9 900 ₽"
                },
                "premium": {
                    "TITLE": "Премиум",
                    "DESCRIPTION": "Для тщательного выбора",
                    "OPTION_1": "Подберём до 12 подходящих анкет работников",
                    "OPTION_2": "Предложим 6 лучших кандидатов на выбор",
                    "OPTION_3": "1 год гарантии — заменим работника бесплатно",
                    "PRICE": "19 900 ₽"
                }
            }
        },
        "algorithm": {
            "TITLE": "Как это работает",
            "step_1": {
                "TITLE": "Вы описываете нам свои требования",
                "DESCRIPTION": "У нас тысячи анкет работников — подберём лучших"
            },
            "step_2": {
                "TITLE": "Мы предлагаем кандидатов на выбор",
                "DESCRIPTION": "Все они уже готовы и согласны с вашими условиями"
            },
            "step_3": {
                "TITLE": "Окончательное решение за вами",
                "DESCRIPTION": "Организуем вам встречу с каждым кандидатом"
            }
        },
        "advantages": {
            "TITLE": "Почему нас выбирают"
        },
        "workers": {
            "TITLE": "Наши работники",
            "ALL_RESUMES": "Все анкеты",
            "TAB_NANNY": "Няня",
            "TAB_HOUSEKEEPER": "Домработница"
        },
        "reviews": {
            "TITLE": "Отзывы наших клиентов",
            "reviews_list": {
                "review_1": {
                    "TITLE": "Очень быстро нашли",
                    "DESCRIPTION": "Искала домработницу на постоянную работу, воспользовалась сервисом подбора от Помогатель.ру. Команда профессионалов! Требования все записали, через пару дней уже готовы были устроить встречу с подходящими кандидатами. В итоге договорились, человек подошёл идеально.Мне очень всё понравилось, быстро и приятно сработали. Буду рекомендовать!",
                    "AUTHOR": "Марина М.",
                    "DATE": "30.08.23",
                    "DATE_RAW": "2023-08-30"
                },
                "review_2": {
                    "TITLE": "Ребенок доволен",
                    "DESCRIPTION": "Делюсь отзывом на Помогатель.ру. Хотели найти няню для ребёнка, обошли много агентств, так нигде и не договорились. Нашла этот сервис рекрутинга, оставила заявку на звонок. Менеджер по телефону мне объяснила, как они ищут, как проверяют кандидатов. Решила попробовать и не разочаровалась. Все няни, которых сервис предложил, подходили под запрос. С каждой нам организовали собеседование, с самой лучшей и подходящей договорились. Всё прошло идеально, ребёнок тоже счастлив :)",
                    "AUTHOR": "Ольга Р.",
                    "DATE": "20.05.23",
                    "DATE_RAW": "2023-05-20"
                },
                "review_3": {
                    "TITLE": "Уже сотрудничаем",
                    "DESCRIPTION": "Работаю вахтой, живу в служебном жилье, искал домработницу. Агентства по подбору персонала просили достаточно много за свои услуги, а вот в Помогателе цена привлекла. Созвонились с рекрутером, я описал, кого ищу. Через пару дней мне уже сообщили, что подобрали кандидатов. Устроили нам встречу, мы пообщались, условия всех устроили. Уже сотрудничаем. Помогателя рекомендую",
                    "AUTHOR": "Виктор С.",
                    "DATE": "11.02.23",
                    "DATE_RAW": "2023-02-11"
                }
            }
        },
        "faq": {
            "TITLE": "Вопросы и ответы",
            "accordions": {
                "acc_1": {
                    "TITLE": "Почему так дёшево?",
                    "DESCRIPTION": "Мы никому не платим за базу кандидатов, она у нас своя — собрана за много лет работы. Найти для вас нужного помощника нашим рекрутерам действительно легко"
                },
                "acc_2": {
                    "TITLE": "А если я сам буду искать?",
                    "DESCRIPTION": "Вы можете зарегистрироваться на сайте Помогатель.ру и найти работника самостоятельно. Но если вы хотите сэкономить время, то лучше обратиться к рекрутеру"
                }, 
                "acc_3": {
                    "TITLE": "Что за гарантия в тарифе Премиум?",
                    "DESCRIPTION": "Если в течение 1 года после найма с помощью рекрутера вам придётся расстаться с работником по любой причине, мы бесплатно подберём нового. Нам важно найти надёжного помощника для вас"
                },
                "acc_4": {
                    "TITLE": "Как проверяем работников?",
                    "DESCRIPTION": "Работники проходят личное интервью с рекрутером, проверку паспорта. А также дополнительно можно запросить проверку благонадежности понравившегося работника, в которую входит 15 различных отчетов"
                }
            }
        },
        "form_rec": {
            "mobile_headers": {
                "ABOUT_WORKER": "О работнике",
                "TARIFF": "Тариф",
                "CONNECTION_DATA": "Данные для связи"
            },
            "labels": {
                "REGION": "Регион, в котором требуется работник",
                "SPECIALIZATION": "Специальность работника",
                "SALARY": "Сколько готовы платить работнику",
                "PHONE": "Ваш номер телефона для связи",
                "NAME": "Как к Вам обращаться",
                "COMMENT": "Любой ваш комментарий",
                "USER_AGREEMENT": "Согласие с",
                "PERSONAL_DATA": "«Политикой в отношении обработки персональных данных»"
            },
            "specializations": {
                "NANNY": "Няня",
                "NURSE": "Сиделка",
                "HOUSEKEEPER": "Домработница",
                "TUTOR": "Репетитор",
                "DRIVER": "Водитель",
                "PSYCH": "Психолог",
                "MASSEUR": "Массажист",
                "PAIR": "Семейная пара"
            },
            "UNTIL": "До",
            "PER_MONTH": "₽/месяц",
            "REC_INFO": "Предварительная информация для рекрутера",
            "NAME_PLACEHOLDER": "Ваше ФИО",
            "tariffs": {
                "premium": {
                    "TITLE": "Премиум",
                    "OPTION_1": "12 подходящих работников, с которыми наш рекрутер предварительно провел интервью",
                    "OPTION_2": "6 собеседований с Вами"
                },
                "standard": {
                    "TITLE": "Стандарт",
                    "OPTION_1": "Подберем вам 6 подходящих работников, с которыми наш рекрутер предварительно провел интервью",
                    "OPTION_2": "Организуем Вам 3 собеседования, с выбранными рабониками"
                }
            }
        }
    }
}